<annotation>
	<folder>tu</folder>
	<filename>000011.jpg</filename>
	<path>F:\tu\000011.jpg</path>
	<source>
		<database>Unknown</database>
	</source>
	<size>
		<width>4016</width>
		<height>6016</height>
		<depth>3</depth>
	</size>
	<segmented>0</segmented>
	<object>
		<name>bd</name>
		<pose>Unspecified</pose>
		<truncated>0</truncated>
		<difficult>0</difficult>
		<bndbox>
			<xmin>1742</xmin>
			<ymin>1192</ymin>
			<xmax>1839</xmax>
			<ymax>1382</ymax>
		</bndbox>
	</object>
	<object>
		<name>bd</name>
		<pose>Unspecified</pose>
		<truncated>0</truncated>
		<difficult>0</difficult>
		<bndbox>
			<xmin>1512</xmin>
			<ymin>2946</ymin>
			<xmax>1619</xmax>
			<ymax>3132</ymax>
		</bndbox>
	</object>
</annotation>
