<annotation>
	<folder>tu</folder>
	<filename>000154.jpg</filename>
	<path>F:\tu\000154.jpg</path>
	<source>
		<database>Unknown</database>
	</source>
	<size>
		<width>5000</width>
		<height>3550</height>
		<depth>3</depth>
	</size>
	<segmented>0</segmented>
	<object>
		<name>bd</name>
		<pose>Unspecified</pose>
		<truncated>0</truncated>
		<difficult>0</difficult>
		<bndbox>
			<xmin>1914</xmin>
			<ymin>1414</ymin>
			<xmax>2118</xmax>
			<ymax>1600</ymax>
		</bndbox>
	</object>
	<object>
		<name>bd</name>
		<pose>Unspecified</pose>
		<truncated>0</truncated>
		<difficult>0</difficult>
		<bndbox>
			<xmin>1229</xmin>
			<ymin>1871</ymin>
			<xmax>1436</xmax>
			<ymax>2007</ymax>
		</bndbox>
	</object>
	<object>
		<name>bd</name>
		<pose>Unspecified</pose>
		<truncated>0</truncated>
		<difficult>0</difficult>
		<bndbox>
			<xmin>1554</xmin>
			<ymin>1843</ymin>
			<xmax>1743</xmax>
			<ymax>2021</ymax>
		</bndbox>
	</object>
</annotation>
