<annotation verified="yes">
	<folder>tu</folder>
	<filename>000227.jpg</filename>
	<path>E:\label\tu\000227.jpg</path>
	<source>
		<database>Unknown</database>
	</source>
	<size>
		<width>4912</width>
		<height>7360</height>
		<depth>3</depth>
	</size>
	<segmented>0</segmented>
	<object>
		<name>bd</name>
		<pose>Unspecified</pose>
		<truncated>0</truncated>
		<difficult>0</difficult>
		<bndbox>
			<xmin>1159</xmin>
			<ymin>253</ymin>
			<xmax>1729</xmax>
			<ymax>922</ymax>
		</bndbox>
	</object>
</annotation>
