<annotation verified="yes">
	<folder>tu</folder>
	<filename>000369.jpg</filename>
	<path>E:\label\tu\000369.jpg</path>
	<source>
		<database>Unknown</database>
	</source>
	<size>
		<width>6016</width>
		<height>4016</height>
		<depth>3</depth>
	</size>
	<segmented>0</segmented>
	<object>
		<name>bd</name>
		<pose>Unspecified</pose>
		<truncated>0</truncated>
		<difficult>0</difficult>
		<bndbox>
			<xmin>2616</xmin>
			<ymin>1916</ymin>
			<xmax>2880</xmax>
			<ymax>2225</ymax>
		</bndbox>
	</object>
</annotation>
